<?xml version = '1.0' encoding = 'UTF-8'?>
<TableProxyOraclev10g class="oracle.dbtools.crest.model.design.storage.oracle.v10g.TableProxyOraclev10g" name="MEMORIAS" directorySegmentName="seg_0" id="BC4DA6C4-17B8-D0A8-8946-255C5B71CDA9">
<createdBy>thamo</createdBy>
<createdTime>2017-07-14 19:26:34 UTC</createdTime>
<ownerDesignName>modelo</ownerDesignName>
<schemaObject>35D58CE6-C0F3-9E10-03CC-909CD99398E3</schemaObject>
<logging>YES</logging>
<partitionedRowMovement>DISABLE</partitionedRowMovement>
<segment>20ACE87C-AFC7-9099-0C0F-33909119C2D7</segment>
<tableSpace>98977902-9EBE-1B0E-8A27-D5CA2996DB9C</tableSpace>
<temporaryChanged>false</temporaryChanged>
<accessDriverType>oracle_loader</accessDriverType>
<rejectLimit></rejectLimit>
<columnProxies itemClass="oracle.dbtools.crest.model.design.storage.oracle.v12c.ColumnProxyOraclev12c">
<ColumnProxy name="IDMEMORIA" id="0DF4CF37-9BDF-65D6-6FC8-EFF6CF9CFFBE">
<createdBy>thamo</createdBy>
<createdTime>2017-07-14 19:26:34 UTC</createdTime>
<ownerDesignName>modelo</ownerDesignName>
</ColumnProxy>
<ColumnProxy name="DESCRICAOMEMORIA" id="2CA8F447-854D-1020-573D-098A5F1B291F">
<createdBy>thamo</createdBy>
<createdTime>2017-07-14 19:26:34 UTC</createdTime>
<ownerDesignName>modelo</ownerDesignName>
</ColumnProxy>
<ColumnProxy name="IDFABRICANTE" id="A37AA20A-059A-6A24-D52C-19841891BBB4">
<createdBy>thamo</createdBy>
<createdTime>2017-07-14 19:26:34 UTC</createdTime>
<ownerDesignName>modelo</ownerDesignName>
</ColumnProxy>
</columnProxies>
<indexProxies>
<IndexProxy class="oracle.dbtools.crest.model.design.storage.oracle.v10g.IndexProxyOraclev10g" name="MEMORIAS_PK" id="622EDC57-F7E6-6211-2452-588F9EDC12AD">
<createdBy>thamo</createdBy>
<createdTime>2017-07-14 19:26:34 UTC</createdTime>
<ownerDesignName>modelo</ownerDesignName>
<schemaObject>35D58CE6-C0F3-9E10-03CC-909CD99398E3</schemaObject>
<segment>0A35B269-4AFE-A412-9ED4-EE0F8C961284</segment>
<tableSpace>98977902-9EBE-1B0E-8A27-D5CA2996DB9C</tableSpace>
</IndexProxy>
</indexProxies>
<foreignKeys>
<ForeignKey class="oracle.dbtools.crest.model.design.storage.oracle.v10g.FKProxyOraclev10g" name="MEMORIAS_FABRICANTES_FK" id="63D63F88-CE31-40A6-5AAD-83077D7282A7">
<createdBy>thamo</createdBy>
<createdTime>2017-07-14 19:26:34 UTC</createdTime>
<ownerDesignName>modelo</ownerDesignName>
</ForeignKey>
</foreignKeys>
<primaryKeys>
<PrimaryKey class="oracle.dbtools.crest.model.design.storage.oracle.v10g.PKProxyOraclev10g" name="MEMORIAS_PK" id="FDDDBB49-5D28-2FDE-EC5F-422BBFDA4047">
<createdBy>thamo</createdBy>
<createdTime>2017-07-14 19:26:34 UTC</createdTime>
<ownerDesignName>modelo</ownerDesignName>
<segment>0A35B269-4AFE-A412-9ED4-EE0F8C961284</segment>
<tableSpace>98977902-9EBE-1B0E-8A27-D5CA2996DB9C</tableSpace>
<existingIndex>622EDC57-F7E6-6211-2452-588F9EDC12AD</existingIndex>
<indexSegment>0A35B269-4AFE-A412-9ED4-EE0F8C961284</indexSegment>
<indexSort>SORTED</indexSort>
<usingIndex>BY INDEX NAME</usingIndex>
</PrimaryKey>
</primaryKeys>
</TableProxyOraclev10g>